autorm
