Metadata-Version: 1.0
Name: autorm
Version: 0.5.4
Summary: A minimal ORM
Home-page: http://github.com/umidev/autorm
Author: Nino Walker
Author-email: nino@urbanmapping.com
License: UNKNOWN
Platform: UNKNOWN
